{
  "trip_summary": {
    "duration": 3,
    "total_budget": 500,
    "actual_expenditure": 407.53,
    "total_travel_time": 416.0,
    "total_satisfaction": 64.6,
    "is_feasible": true,
    "starting_hotel": "Marina Bay Sands Singapore"
  },
  "days": [
    {
      "day": 1,
      "date": "2025-03-27",
      "locations": [
        {
          "name": "Marina Bay Sands Singapore",
          "type": "hotel",
          "arrival_time": "09:00",
          "departure_time": "09:00",
          "lat": 1.2837575,
          "lng": 103.8591065,
          "transit_from_prev": null,
          "transit_duration": 0,
          "transit_cost": 0,
          "duration": 0,
          "satisfaction": 0,
          "cost": 0,
          "rest_duration": 0,
          "actual_arrival_time": null
        },
        {
          "name": "Changi Beach Park",
          "type": "attraction",
          "arrival_time": "09:31",
          "departure_time": "11:17",
          "lat": 1.3912863,
          "lng": 103.9905464,
          "transit_from_prev": "drive",
          "transit_duration": 31,
          "transit_cost": 20.92,
          "duration": 106,
          "satisfaction": 3.7,
          "cost": 0.35,
          "rest_duration": 0,
          "actual_arrival_time": null,
          "description": "Attraction with satisfaction rating 3.7/10",
          "entrance_fee": 0.35
        },
        {
          "name": "Science Centre Singapore",
          "type": "attraction",
          "arrival_time": "11:59",
          "departure_time": "13:21",
          "lat": 1.3331687,
          "lng": 103.7356443,
          "transit_from_prev": "drive",
          "transit_duration": 43,
          "transit_cost": 31.84,
          "duration": 82,
          "satisfaction": 2.4,
          "cost": 0.28,
          "rest_duration": 0,
          "actual_arrival_time": null,
          "description": "Attraction with satisfaction rating 2.4/10",
          "entrance_fee": 0.28
        },
        {
          "name": "Tekka Centre",
          "type": "hawker",
          "arrival_time": "13:48",
          "departure_time": "14:48",
          "lat": 1.3063839,
          "lng": 103.8507014,
          "transit_from_prev": "drive",
          "transit_duration": 27,
          "transit_cost": 17.28,
          "duration": 60,
          "satisfaction": 4.7,
          "cost": 3.0,
          "rest_duration": 0,
          "actual_arrival_time": null,
          "meal_type": "lunch",
          "description": "Food center with rating 4.7/5",
          "meal_cost": 3.0
        },
        {
          "name": "Marina Barrage",
          "type": "attraction",
          "arrival_time": "15:02",
          "departure_time": "16:08",
          "lat": 1.2805168,
          "lng": 103.8714399,
          "transit_from_prev": "drive",
          "transit_duration": 14,
          "transit_cost": 8.18,
          "duration": 66,
          "satisfaction": 2.2,
          "cost": 1.57,
          "rest_duration": 0,
          "actual_arrival_time": null,
          "description": "Attraction with satisfaction rating 2.2/10",
          "entrance_fee": 1.57
        },
        {
          "name": "St Andrew's Cathedral",
          "type": "attraction",
          "arrival_time": "16:22",
          "departure_time": "17:36",
          "lat": 1.2923914,
          "lng": 103.8522543,
          "transit_from_prev": "drive",
          "transit_duration": 14,
          "transit_cost": 7.4,
          "duration": 74,
          "satisfaction": 3.6,
          "cost": 3.73,
          "rest_duration": 0,
          "actual_arrival_time": null,
          "description": "Attraction with satisfaction rating 3.6/10",
          "entrance_fee": 3.73
        },
        {
          "name": "Tekka Centre",
          "type": "hawker",
          "arrival_time": "18:00",
          "departure_time": "19:00",
          "lat": 1.3063839,
          "lng": 103.8507014,
          "transit_from_prev": "drive",
          "transit_duration": 10,
          "transit_cost": 5.84,
          "duration": 60,
          "satisfaction": 4.7,
          "cost": 3.0,
          "rest_duration": 13,
          "actual_arrival_time": "17:47",
          "meal_type": "dinner",
          "description": "Food center with rating 4.7/5. Arrived at 17:47 and waited 13 minutes for opening time.",
          "meal_cost": 3.0
        },
        {
          "name": "Marina Bay Sands Singapore",
          "type": "hotel",
          "position": "end",
          "arrival_time": "19:35",
          "departure_time": "19:35",
          "lat": 1.2837575,
          "lng": 103.8591065,
          "transit_from_prev": "transit",
          "transit_duration": 35,
          "transit_cost": 1.4,
          "satisfaction": 0,
          "cost": 0,
          "rest_duration": 0
        }
      ]
    },
    {
      "day": 2,
      "date": "2025-03-28",
      "locations": [
        {
          "name": "Marina Bay Sands Singapore",
          "type": "hotel",
          "arrival_time": "09:00",
          "departure_time": "09:00",
          "lat": 1.2837575,
          "lng": 103.8591065,
          "transit_from_prev": null,
          "transit_duration": 0,
          "transit_cost": 0,
          "duration": 0,
          "satisfaction": 0,
          "cost": 0,
          "rest_duration": 0,
          "actual_arrival_time": null
        },
        {
          "name": "MacRitchie Reservoir",
          "type": "attraction",
          "arrival_time": "09:19",
          "departure_time": "10:25",
          "lat": 1.3447621,
          "lng": 103.8223506,
          "transit_from_prev": "drive",
          "transit_duration": 19,
          "transit_cost": 13.64,
          "duration": 66,
          "satisfaction": 3.8,
          "cost": 4.42,
          "rest_duration": 0,
          "actual_arrival_time": null,
          "description": "Attraction with satisfaction rating 3.8/10",
          "entrance_fee": 4.42
        },
        {
          "name": "Asian Civilisations Museum",
          "type": "attraction",
          "arrival_time": "10:44",
          "departure_time": "12:29",
          "lat": 1.2874969,
          "lng": 103.8513861,
          "transit_from_prev": "drive",
          "transit_duration": 20,
          "transit_cost": 13.12,
          "duration": 105,
          "satisfaction": 2.3,
          "cost": 3.25,
          "rest_duration": 0,
          "actual_arrival_time": null,
          "description": "Attraction with satisfaction rating 2.3/10",
          "entrance_fee": 3.25
        },
        {
          "name": "Fort Canning Park",
          "type": "attraction",
          "arrival_time": "12:36",
          "departure_time": "14:35",
          "lat": 1.2943876,
          "lng": 103.8458033,
          "transit_from_prev": "drive",
          "transit_duration": 6,
          "transit_cost": 5.84,
          "duration": 119,
          "satisfaction": 2.9,
          "cost": 6.1,
          "rest_duration": 0,
          "actual_arrival_time": null,
          "description": "Attraction with satisfaction rating 2.9/10",
          "entrance_fee": 6.1
        },
        {
          "name": "East Coast Lagoon Food Village",
          "type": "hawker",
          "arrival_time": "14:53",
          "departure_time": "15:53",
          "lat": 1.3069299,
          "lng": 103.9349594,
          "transit_from_prev": "drive",
          "transit_duration": 19,
          "transit_cost": 13.64,
          "duration": 60,
          "satisfaction": 4.6,
          "cost": 1.5,
          "rest_duration": 0,
          "actual_arrival_time": null,
          "meal_type": "lunch",
          "description": "Food center with rating 4.6/5",
          "meal_cost": 1.5
        },
        {
          "name": "AJ Hackett Sentosa",
          "type": "attraction",
          "arrival_time": "16:17",
          "departure_time": "17:48",
          "lat": 1.2551584,
          "lng": 103.8133212,
          "transit_from_prev": "drive",
          "transit_duration": 23,
          "transit_cost": 18.32,
          "duration": 91,
          "satisfaction": 2.4,
          "cost": 5.99,
          "rest_duration": 0,
          "actual_arrival_time": null,
          "description": "Attraction with satisfaction rating 2.4/10",
          "entrance_fee": 5.99
        },
        {
          "name": "Amoy Street Food Centre",
          "type": "hawker",
          "arrival_time": "18:02",
          "departure_time": "19:02",
          "lat": 1.2794274,
          "lng": 103.8467957,
          "transit_from_prev": "drive",
          "transit_duration": 15,
          "transit_cost": 8.96,
          "duration": 60,
          "satisfaction": 4.5,
          "cost": 4.5,
          "rest_duration": 0,
          "actual_arrival_time": null,
          "meal_type": "dinner",
          "description": "Food center with rating 4.5/5",
          "meal_cost": 4.5
        },
        {
          "name": "Marina Bay Sands Singapore",
          "type": "hotel",
          "position": "end",
          "arrival_time": "19:19",
          "departure_time": "19:19",
          "lat": 1.2837575,
          "lng": 103.8591065,
          "transit_from_prev": "transit",
          "transit_duration": 17,
          "transit_cost": 1.19,
          "satisfaction": 0,
          "cost": 0,
          "rest_duration": 0
        }
      ]
    },
    {
      "day": 3,
      "date": "2025-03-29",
      "locations": [
        {
          "name": "Marina Bay Sands Singapore",
          "type": "hotel",
          "arrival_time": "09:00",
          "departure_time": "09:00",
          "lat": 1.2837575,
          "lng": 103.8591065,
          "transit_from_prev": null,
          "transit_duration": 0,
          "transit_cost": 0,
          "duration": 0,
          "satisfaction": 0,
          "cost": 0,
          "rest_duration": 0,
          "actual_arrival_time": null
        },
        {
          "name": "Coney Island Park",
          "type": "attraction",
          "arrival_time": "09:23",
          "departure_time": "11:06",
          "lat": 1.4092951,
          "lng": 103.9216496,
          "transit_from_prev": "drive",
          "transit_duration": 23,
          "transit_cost": 17.02,
          "duration": 103,
          "satisfaction": 3.5,
          "cost": 11.44,
          "rest_duration": 0,
          "actual_arrival_time": null,
          "description": "Attraction with satisfaction rating 3.5/10",
          "entrance_fee": 11.44
        },
        {
          "name": "Boat Quay",
          "type": "attraction",
          "arrival_time": "11:29",
          "departure_time": "13:28",
          "lat": 1.2859963,
          "lng": 103.8501608,
          "transit_from_prev": "drive",
          "transit_duration": 24,
          "transit_cost": 17.02,
          "duration": 119,
          "satisfaction": 3.8,
          "cost": 12.94,
          "rest_duration": 0,
          "actual_arrival_time": null,
          "description": "Attraction with satisfaction rating 3.8/10",
          "entrance_fee": 12.94
        },
        {
          "name": "Chinatown Complex Food Centre",
          "type": "hawker",
          "arrival_time": "13:36",
          "departure_time": "14:36",
          "lat": 1.2819187,
          "lng": 103.8433447,
          "transit_from_prev": "drive",
          "transit_duration": 8,
          "transit_cost": 5.32,
          "duration": 60,
          "satisfaction": 4.5,
          "cost": 5.0,
          "rest_duration": 0,
          "actual_arrival_time": null,
          "meal_type": "lunch",
          "description": "Food center with rating 4.5/5",
          "meal_cost": 5.0
        },
        {
          "name": "Peranakan Museum",
          "type": "attraction",
          "arrival_time": "14:46",
          "departure_time": "15:51",
          "lat": 1.2943669,
          "lng": 103.8490391,
          "transit_from_prev": "drive",
          "transit_duration": 10,
          "transit_cost": 5.84,
          "duration": 65,
          "satisfaction": 3.6,
          "cost": 15.23,
          "rest_duration": 0,
          "actual_arrival_time": null,
          "description": "Attraction with satisfaction rating 3.6/10",
          "entrance_fee": 15.23
        },
        {
          "name": "Sungei Buloh Wetland Reserve",
          "type": "attraction",
          "arrival_time": "16:35",
          "departure_time": "17:21",
          "lat": 1.4464304,
          "lng": 103.723404,
          "transit_from_prev": "drive",
          "transit_duration": 44,
          "transit_cost": 27.94,
          "duration": 46,
          "satisfaction": 2.7,
          "cost": 14.05,
          "rest_duration": 0,
          "actual_arrival_time": null,
          "description": "Attraction with satisfaction rating 2.7/10",
          "entrance_fee": 14.05
        },
        {
          "name": "Maxwell Food Centre",
          "type": "hawker",
          "arrival_time": "18:01",
          "departure_time": "19:01",
          "lat": 1.2803361,
          "lng": 103.844767,
          "transit_from_prev": "drive",
          "transit_duration": 39,
          "transit_cost": 29.24,
          "duration": 60,
          "satisfaction": 4.5,
          "cost": 25.0,
          "rest_duration": 0,
          "actual_arrival_time": null,
          "meal_type": "dinner",
          "description": "Food center with rating 4.5/5",
          "meal_cost": 25.0
        },
        {
          "name": "Marina Bay Sands Singapore",
          "type": "hotel",
          "position": "end",
          "arrival_time": "19:23",
          "departure_time": "19:23",
          "lat": 1.2837575,
          "lng": 103.8591065,
          "transit_from_prev": "transit",
          "transit_duration": 22,
          "transit_cost": 1.19,
          "satisfaction": 0,
          "cost": 0,
          "rest_duration": 0
        }
      ]
    }
  ],
  "attractions_visited": [
    "Asian Civilisations Museum",
    "Peranakan Museum",
    "Fort Canning Park",
    "Boat Quay",
    "MacRitchie Reservoir",
    "Sungei Buloh Wetland Reserve",
    "St Andrew's Cathedral",
    "Science Centre Singapore",
    "Marina Barrage",
    "Coney Island Park",
    "Changi Beach Park",
    "AJ Hackett Sentosa"
  ],
  "budget_breakdown": {
    "attractions": 79.35,
    "meals": 42.0,
    "transportation": 271.14000000000004
  },
  "transport_summary": {
    "total_duration": 463,
    "total_cost": 271.14000000000004
  },
  "rest_summary": {
    "total_rest_duration": 13
  }
}